huggingfs/__init__.py
huggingfs/main.py
huggingfs-0.5.dist-info/METADATA
huggingfs-0.5.dist-info/WHEEL
huggingfs-0.5.dist-info/entry_points.txt
huggingfs-0.5.dist-info/top_level.txt
huggingfs-0.5.dist-info/RECORD
